e4clim/__init__.py
e4clim/_version.py
e4clim/application.py
e4clim/config.py
e4clim/plot.py
e4clim/typing.py
e4clim/api/__init__.py
e4clim/api/calendar_italy.py
e4clim/api/cbs.py
e4clim/api/cordex.py
e4clim/api/datagouv_french_regions.py
e4clim/api/eco2mix.py
e4clim/api/eea.py
e4clim/api/eirgrid.py
e4clim/api/elia.py
e4clim/api/energidataservice_dk.py
e4clim/api/energimyndigheten.py
e4clim/api/entsoe.py
e4clim/api/esgf.py
e4clim/api/gadm.py
e4clim/api/gisco.py
e4clim/api/gme.py
e4clim/api/gov_uk_dukes.py
e4clim/api/istat.py
e4clim/api/merra2.py
e4clim/api/natomraden.py
e4clim/api/reader.py
e4clim/api/reseaux_energies.py
e4clim/api/smard.py
e4clim/api/terna.py
e4clim/api/workalendar.py
e4clim/build/__init__.py
e4clim/build/application.py
e4clim/build/base.py
e4clim/build/context_component.py
e4clim/build/context_optimizer.py
e4clim/build/context_result.py
e4clim/build/logger.py
e4clim/build/strategy.py
e4clim/container/__init__.py
e4clim/container/base.py
e4clim/container/data_source.py
e4clim/container/geo_data_source.py
e4clim/container/geo_multi_data_source.py
e4clim/container/gridded_data_source.py
e4clim/container/mask.py
e4clim/container/multi_data_source.py
e4clim/container/optimizer.py
e4clim/container/optimizer_data_source.py
e4clim/container/optimizer_multi_data_source.py
e4clim/container/parsing_data_source.py
e4clim/container/parsing_multi_data_source.py
e4clim/container/parsing_single_data_source.py
e4clim/container/result_data_source.py
e4clim/container/single_data_source.py
e4clim/container/strategy.py
e4clim/container/task_manager.py
e4clim/context/__init__.py
e4clim/context/base.py
e4clim/context/context_component.py
e4clim/context/context_data_sources.py
e4clim/context/context_geo_data_source.py
e4clim/context/context_multi_data_sources.py
e4clim/context/context_multi_optimizer.py
e4clim/context/context_optimizer.py
e4clim/context/context_result.py
e4clim/context/context_single_data_sources.py
e4clim/context/mediator.py
e4clim-1.2.0.dist-info/LICENSE.txt
e4clim-1.2.0.dist-info/METADATA
e4clim-1.2.0.dist-info/WHEEL
e4clim-1.2.0.dist-info/entry_points.txt
e4clim-1.2.0.dist-info/top_level.txt
e4clim-1.2.0.dist-info/RECORD
